programs/__init__.py
programs/excel2json.py
programs/hjxdataconverter.py
programs/html2json.py
programs/json2excel.py
programs/json2html.py
hjxdataconverter-1.0.0.dist-info/METADATA
hjxdataconverter-1.0.0.dist-info/WHEEL
hjxdataconverter-1.0.0.dist-info/entry_points.txt
hjxdataconverter-1.0.0.dist-info/top_level.txt
hjxdataconverter-1.0.0.dist-info/RECORD
