Metadata-Version: 2.1
Name: hjxdataconverter
Version: 1.0.0
Summary: Python command line program for converting data between json, html and excel
Home-page: UNKNOWN
Author: Isabel Sandstrøm
Author-email: isabel@hermit.no
License: UNKNOWN
Platform: UNKNOWN
Classifier: Programming Language :: Python :: 3
Classifier: License :: OSI Approved :: MIT License
Classifier: Operating System :: OS Independent
Requires-Python: >=3.6
